{
  "project_info": {
    "project_number": "650429025557",
    "project_id": "fantasy-f1-ebeeb",
    "storage_bucket": "fantasy-f1-ebeeb.firebasestorage.app"
  },
  "client": [
    {
      "client_info": {
        "mobilesdk_app_id": "1:650429025557:android:47b43e18e2318194ed2d1c",
        "android_client_info": {
          "package_name": "com.exemple.fantasy_f1_app"
        }
      },
      "oauth_client": [],
      "api_key": [
        {
          "current_key": "AIzaSyD5_TAmTmShSUjb5Mp-vyibiZZEyfH_5S8"
        }
      ],
      "services": {
        "appinvite_service": {
          "other_platform_oauth_client": []
        }
      }
    }
  ],
  "configuration_version": "1"
}